{"Registers":[
{
  "Name": "integral",
  "Address": 0,
  "RegionSize": 1,
  "Description": "",
  "Category": "Undefined"
},
{
  "Name": "runcfg",
  "Address": 1,
  "RegionSize": 1,
  "Description": "",
  "Category": "Undefined"
},
{
  "Name": "counter",
  "Address": 2,
  "RegionSize": 1,
  "Description": "",
  "Category": "Undefined"
},
{
  "Name": "reset",
  "Address": 3,
  "RegionSize": 1,
  "Description": "",
  "Category": "Undefined"
},
{
  "Name": "strobecount",
  "Address": 4,
  "RegionSize": 1,
  "Description": "",
  "Category": "Undefined"
},
{
  "Name": "trigcount",
  "Address": 5,
  "RegionSize": 1,
  "Description": "",
  "Category": "Undefined"
},
{
  "Name": "peak",
  "Address": 6,
  "RegionSize": 1,
  "Description": "",
  "Category": "Undefined"
}],
"MMCComponents":[],"Device":"DT5560","Project":"ComputerInteractionTest"}